{
  "name": "Thomson Reuters ONESOURCE - Indirect Tax Compliance",
  "url": "https://tax.thomsonreuters.com/en/onesource/indirect-tax/compliance",
  "timestamp": "2026-06-05T02:32:18.383691+00:00",
  "timestamp_human": "June 05, 2026 at 02:32 AM UTC",
  "content_hash": "0f237dcef0bf5d9ff3a8669fead9f504838af49871235b19a043d0028df014df",
  "content": "Our technology powers the professionals who are shaping the world.\nMeet the changemakers\nSkip to main content\nThomson Reuters\nSolutions\nProducts\nPurchase\nResources\nHelp\nSign into your products\nSign in to manage account\nLaw firms\nCorporations\nTax, audit & accounting firms\nGovernment\nPartnerships & alliances\nBy use case\nBy practice area\nAI for legal\nLegal research & guidance\nLegal forms\nBusiness development\nLegal data & document management\nBusiness practice & procedure\nDrafting software, service & guidance\nEvidence\nTrial readiness, process & case guidance\nView all\nBusiness & commercial law\nCivil litigation\nCriminal defense\nFamily law\nCustomer story\nJustly Prudent achieves 5 times the ROI with CoCounsel\nLearn how Justly Prudent used CoCounsel and Westlaw AI to achieve exceptional return on investment (ROI) \u2014 increasing litigation capacity by 100%.\nRead case study\nCorporate legal professionals\nCorporate tax & trade professionals\nCorporate risk & fraud professionals\nC-suite\nDraft, review & legal analysis\nLegal research & advisory\nDue diligence & compliance\nSpend & matter management\nView all\nCross-border trade\nPeriodic financial close\nTax, research & insights\nTransactional compliance\nView all\nCollections & recovery\nContinuous monitoring & fraud detection\nInvestigations\nOnboarding due diligence & fraud prevention\nView all\nIntelligent compliance network\nChief financial officers and heads of tax\nGeneral counsel and chief legal officers\nChief risk officers\nCustomer story\nAI that delivers\nSee how Brinks used CoCounsel to streamline legal work, cut outside counsel spend, and strengthen global operations.\nRead case study\nTax workflow\nAudit workflow\nProfessional development\nCustomer story\nSpeed meets confidence\nDiscover how Harris, Hardy & Johnstone reduced hour-long reviews into minutes with CoCounsel.\nRead case study\nLegal professionals\nLaw enforcement\nCity attorneys\nCourts\nProsecutors\nPublic defenders\nCustomer story\nStreamlined matter management\nSee how the Pascua Yaqui Tribe used HighQ to transform legal matter management.\nRead case study\nAbout our Partnership program\nBecome a partner\nFind a partner\nInsights\nCompliance without complexity\nLearn how Oracle users consolidate compliance into one platform that reduces complexity while scaling tax and trade.\nRead blog\nLegal\nTax, audit & accounting\nGlobal trade & supply\nRisk & fraud\nBooks\nCoCounsel Legal\nIntegrate research, analysis, and drafting with professional-grade AI grounded in trusted Westlaw and Practical Law content.\nWestlaw\nFind legal answers faster with trusted research software powered by 150 years of expertise and AI.\nPractical Law\nDeliver confident legal work with AI powered by more than 650 attorney-editors\u2019 guides, templates, and checklists.\nHighQ\nAccelerate legal delivery through secure collaboration, automated workflows, and AI-powered client engagement.\nLegal Tracker\nMaximize legal efficiency while reducing annual spend through AI-powered matter management.\nView all\nWestlaw Advantage\nMove from research to strategy faster with agentic AI and comprehensive, verified Westlaw content.\nWestlaw Edge\nExpedite complex legal research with AI tools that deliver precise, verified answers and strategic insights.\nFeatured\nCoCounsel Legal\nComplete legal work faster with AI that unites research, analysis, and drafting in one seamless experience.\nLearn more\nTax, audit & accounting\nIncrease efficiency, mitigate risk, and provide premium client services with enhanced AI capabilities and expert insights.\nCorporate tax\nProcess high-volume transactions accurately with scalable tax software built for multi-entity corporate environments.\nCoCounsel Audit\nStandardize audit workflows with AI-powered automation that delivers verifiable, citation-backed insights.\nCoCounsel Tax\nComplete tax research and client deliverables faster using AI that centralizes trusted sources and firm data.\nGuided Assurance\nComplete audit engagements efficiently and ensure compliance with automated software that identifies risks using AI.\nReady to Advise\nTurn client data into actionable tax strategies with AI that identifies opportunities and guides implementation.\nReady to Review\nScale tax capacity with AI that automates 1040 return preparation and eliminates manual data-entry tasks.\nSafeSend\nScale tax capacity with AI that automates 1040 return preparation and eliminates manual data-entry tasks.\nView all\nCoCounsel Tax\nComplete tax research and client deliverables faster using AI that centralizes trusted sources and firm data.\nONESOURCE Determination\nEnsure accurate tax calculations across all systems with a certified, automated software for global indirect taxes.\nONESOURCE Income Tax\nFile accurate corporate tax returns faster with trusted software for federal, state, and international compliance.\nONESOURCE Indirect Compliance\nCentralize indirect tax compliance with automated software for VAT, GST, and sales tax across all jurisdictions.\nONESOURCE Pagero\nStreamline e-invoicing compliance globally with integrated software that centralizes tax data and automates reporting.\nONESOURCE Tax Provision\nExpedite financial close with automated software that calculates tax estimates in seconds and streamlines reporting.\nView all\nFeatured\nCoCounsel Tax\nManage export compliance, screening, clearance, and documents in one workflow.\nLearn more\nONESOURCE Foreign Trade Zone Management\nMaximize duty savings and improve cash flow with software that centralizes supply-chain data and automates compliance.\nONESOURCE Global Classification AI\nAutomate trade compliance with an AI software that delivers fast, accurate product classifications for import and export.\nONESOURCE Global Trade Content\nPower global trade compliance with trusted content, rapid updates, and broad coverage.\nONESOURCE Denied Party Screening\nMinimize sanctions risk with automated denied-party screening across more than 750 global lists.\nONESOURCE Free Trade Agreement Management\nReduce duties and simplify free-trade-agreement qualifications with less manual effort.\nONESOURCE Export Management\nManage export compliance, screening, clearance, and documents in one workflow.\nView all\nFeatured\nGlobal Classification AI\nEliminate the complexity of global trade compliance with AI-powered Harmonized System (HS) code classification that's fast, accurate, and always audit ready.\nLearn more\nCLEAR\nAdvance your investigations with trusted public-records technology that reveals critical connections in one platform.\nCLEAR Investigate\nSurface critical connections faster with AI-driven research workflows integrated with premium public-records data.\nCLEAR Adverse Media\nScreen for risky individuals and businesses with automated monitoring of adverse media across the globe.\nCLEAR ID Confirm\nVerify identities faster with customizable software that delivers confidence scores across public-records data.\nCLEAR Risk Inform\nQuickly identify risk with customizable assessment software that delivers calculated scores and adverse flags.\nFraud Detect\nDetect complex fraud schemes with machine-learning technology that delivers risk scoring and actionable insights.\nView all\nFeatured\nCLEAR Investigate\nSurface critical connections faster with AI-driven research workflows integrated with premium public records data.\nLearn more\nLegal books\nTax books\nCategory\nJurisdiction\nShop all\nBrand\nOrganization\nPractice area\nShop all\nFeatured\nTax Quickfinder\nSimplify tax research with quick-reference handbooks that deliver accurate answers in a concise, practical format.\nLearn more\nLaw firms under 10 attorneys\nLaw firms over 10 attorneys\nCorporations\nTax, audit & accounting firms\nGovernment\nBooks\nWestlaw Edge\nWestlaw Edge with AI-Assisted Research\nWestlaw Advantage\nWestlaw Advantage with CoCounsel Essentials\nCoCounsel Essentials\nCoCounsel Legal\nPractical Law\nPractical Law Dynamic Tool Set with CoCounsel Essentials\nTailored solutions\nSmall firms\nDiscover legal research and drafting tools designed to help solo practitioners and small firms compete and scale efficiently.\nLearn more\nContact us about plans for law firms\nDiscover the right plan for your law firm with the help of a knowledgeable sales representative.\nFeatured\nCoCounsel Legal\nComplete legal work faster with AI that unites research, analysis, and drafting in one seamless experience.\nLearn more\nWestlaw Edge\nWestlaw Advantage\nCoCounsel Essentials\nCoCounsel Legal\nPractical Law\nPractical Law Dynamic Tool Set with CoCounsel Essentials\nGet started\nContact sales\nConnect with our sales team to explore legal solutions tailored to your professional needs and business goals.\nContact us\nContact us about plans for tax, audit & accounting firms\nGet expert guidance on tax, audit, and accounting solutions for your firm.\nFeatured\nCoCounsel Tax\nManage export compliance, screening, clearance, and documents in one workflow.\nLearn more\nWestlaw Edge\nCoCounsel Essentials\nPractical Law\nGet started\nContact sales\nConnect with our sales team to explore legal solutions tailored to your professional needs and business goals.\nContact us\nLegal books\nTax books\nBlack's Law Dictionary\nProView e-books\nShop all\nAudit & accounting titles\nBest sellers\nTax Quickfinder\nShop all\nFeatured\nProView\nAccess your entire professional library anywhere, anytime with the only e-reader platform built from the ground up for legal and tax professionals.\nLearn more\nInsights\nEvents\nProduct training\nProduct communities\nDevelopers\nThomson Reuters Institute\nAccess expert research and trends that empower professionals to navigate industry transformation with confidence.\nInnovation @ Thomson Reuters\nLearn how innovation powers the future of professional work through technology and strategic transformation.\nLegal insights\nExplore thought leadership and practical insights that help legal professionals navigate industry changes.\nTax insights\nNavigate tax complexities with expert commentary, news, and analysis for accounting professionals nationwide.\nInsights\nHuman intelligence\nSee how expert human intelligence shapes "
}